click_shell/__init__.py
click_shell/_cmd.py
click_shell/_compat.py
click_shell/core.py
click_shell/decorators.py
click_shell-2.1.dist-info/LICENSE
click_shell-2.1.dist-info/METADATA
click_shell-2.1.dist-info/WHEEL
click_shell-2.1.dist-info/top_level.txt
click_shell-2.1.dist-info/RECORD
