Metadata-Version: 2.1
Name: click-shell
Version: 2.1
Summary: An extension to click that easily turns your click app into a shell utility
Home-page: https://github.com/clarkperkins/click-shell
Author: Clark Perkins
Author-email: r.clark.perkins@gmail.com
License: BSD
Platform: UNKNOWN
Classifier: Development Status :: 5 - Production/Stable
Classifier: Intended Audience :: Developers
Classifier: License :: OSI Approved :: BSD License
Classifier: Operating System :: OS Independent
Classifier: Topic :: Software Development :: User Interfaces
Classifier: Topic :: System :: Shells
Classifier: Topic :: Utilities
Classifier: Programming Language :: Python
Classifier: Programming Language :: Python :: 2
Classifier: Programming Language :: Python :: 2.7
Classifier: Programming Language :: Python :: 3
Classifier: Programming Language :: Python :: 3.6
Classifier: Programming Language :: Python :: 3.7
Classifier: Programming Language :: Python :: 3.8
Classifier: Programming Language :: Python :: 3.9
Provides-Extra: readline
Provides-Extra: windows
License-File: LICENSE
